WeightedMarkov/MarkovBase.py
WeightedMarkov/NaiveMarkov.py
WeightedMarkov/WeightedHOMVMarkov.py
WeightedMarkov/WeightedMarkov.py
WeightedMarkov-0.124.dist-info/DESCRIPTION.rst
WeightedMarkov-0.124.dist-info/METADATA
WeightedMarkov-0.124.dist-info/RECORD
WeightedMarkov-0.124.dist-info/WHEEL
WeightedMarkov-0.124.dist-info/metadata.json
WeightedMarkov-0.124.dist-info/top_level.txt
