Metadata-Version: 2.0
Name: WeightedMarkov
Version: 0.124
Summary: Implementation of Weighted Markov Chain as in Wai Ki Ching, Eric S. Fung, Michael K. Ng
Home-page: https://github.com/sada-narayanappa/WeightedMarkov.git
Author: Code Red
Author-email: sada@geospaces.org
License: MIT
Platform: UNKNOWN
Classifier: Development Status :: 3 - Alpha
Classifier: Intended Audience :: Developers
Classifier: License :: OSI Approved :: MIT License
Classifier: Programming Language :: Python :: 3
Classifier: Programming Language :: Python :: 3.2
Classifier: Programming Language :: Python :: 3.3
Classifier: Programming Language :: Python :: 3.4
Requires-Dist: Jupytils
Requires-Dist: cvxopt
